fyers_helper/__init__.py
fyers_helper/backtest_util.py
fyers_helper/fyers_util.py
fyers_helper/trading_util.py
fyers_helper-0.1.12.dist-info/METADATA
fyers_helper-0.1.12.dist-info/WHEEL
fyers_helper-0.1.12.dist-info/RECORD
