Metadata-Version: 2.4
Name: fyers_helper
Version: 0.1.12
Summary: 
Author: Your Name
Author-email: you@example.com
Requires-Python: >=3.10,<4.0
Classifier: Programming Language :: Python :: 3
Classifier: Programming Language :: Python :: 3.10
Classifier: Programming Language :: Python :: 3.11
Classifier: Programming Language :: Python :: 3.12
Classifier: Programming Language :: Python :: 3.13
Classifier: Programming Language :: Python :: 3.14
Requires-Dist: fyers-apiv3 (>=3.1,<4.0)
Requires-Dist: pandas (>=2.3,<3.0)
Requires-Dist: retry (>=0.9.2,<0.10.0)
Requires-Dist: tqdm (>=4.67.1,<5.0.0)
